cairo_toolkit/__init__.py
cairo_toolkit/generator.py
cairo_toolkit/interface_parser.py
cairo_toolkit/order_imports.py
cairo_toolkit/utils.py
src/cli.py
src/logic.py
cairo_toolkit-1.0.1.dist-info/entry_points.txt
cairo_toolkit-1.0.1.dist-info/LICENSE
cairo_toolkit-1.0.1.dist-info/WHEEL
cairo_toolkit-1.0.1.dist-info/METADATA
cairo_toolkit-1.0.1.dist-info/RECORD
