Metadata-Version: 2.1
Name: cairo-toolkit
Version: 1.0.1
Summary: A set of useful tools for cairo / starknet development.
License: MIT
Author: msaug
Author-email: msaug@protonmail.com
Requires-Python: >=3.9,<4.0
Classifier: License :: OSI Approved :: MIT License
Classifier: Programming Language :: Python :: 3
Classifier: Programming Language :: Python :: 3.9
Classifier: Programming Language :: Python :: 3.10
Requires-Dist: cairo-lang (>=0.10.0,<0.11.0)
Requires-Dist: click (==8.1.3)
Requires-Dist: toml (==0.10.2)
